gencalc/__init__.py
gencalc/gencalc.py
gencalc-1.0.3.dist-info/licenses/LICENSE
gencalc-1.0.3.dist-info/METADATA
gencalc-1.0.3.dist-info/WHEEL
gencalc-1.0.3.dist-info/top_level.txt
gencalc-1.0.3.dist-info/RECORD
